{
    "menu": "Penguji",
    "filterPeriode": "2020/2021 Genap",
    "filterJalur": "Prestasi",
    "filterGelombang": "Gelombang 4",
    "filterSistemKuliah": "Reguler B",
    "filterSeleksi1": "TES CBT",
    "filterSeleksi2": "TES POTENSI AKADEMIK",
    "cariDosen1": "andr",
    "namaDosen1": "1001079001 - ANDREW SHANDY UTAMA",
    "cariDosen2": "yetti",
    "namaDosen2": "1001106501 - YETTI",

    "alertGagalSimpan": "Pengubahan data Penguji Seleksi gagal",
    "alertSimpan": "Penambahan data Penguji Seleksi berhasil",
    "alertUbah": "Pengubahan data Penguji Seleksi berhasil",
    "alertHapus": "Penghapusan data Penguji Seleksi berhasil",
    "modalHapus":"Apakah anda yakin akan menghapus data ini?",
    "modalPeringatan":"Mohon mengisi isian yang bergaris merah",
    "alertBentrok": "Bentrok Dengan Seleksi"
}